jsoninja/__init__.py
jsoninja/compare.py
jsoninja/core.py
jsoninja/exceptions.py
jsoninja/utils.py
tests/__init__.py
tests/conftest.py
tests/test_compare.py
tests/test_core.py
tests/test_utils.py
jsonavigator-1.1.0.dist-info/LICENSE
jsonavigator-1.1.0.dist-info/METADATA
jsonavigator-1.1.0.dist-info/WHEEL
jsonavigator-1.1.0.dist-info/top_level.txt
jsonavigator-1.1.0.dist-info/RECORD
