Metadata-Version: 2.1
Name: jsonavigator
Version: 1.1.0
Summary: A Python package for handling nested JSON structures.
Home-page: https://github.com/Nikhil-Singh-2503/JSONavigator
Author: Nikhil Singh
Author-email: nikhilraj7654@gmail.com
License: UNKNOWN
Platform: UNKNOWN
Classifier: Programming Language :: Python
Classifier: Programming Language :: Python :: 3
Classifier: License :: OSI Approved :: MIT License
Classifier: Operating System :: OS Independent
Classifier: Intended Audience :: Developers
Classifier: Topic :: Utilities
Classifier: Topic :: File Formats
Classifier: Topic :: File Formats :: JSON
Classifier: Topic :: Software Development :: Libraries
Classifier: Topic :: Software Development :: Libraries :: Python Modules
Requires-Python: >=3.8
